LICENSE
MANIFEST.in
setup.py
cmsplugin_plaintext/.DS_Store
cmsplugin_plaintext/__init__.py
cmsplugin_plaintext/cms_plugins.py
cmsplugin_plaintext/models.py
cmsplugin_plaintext/migrations/0001_initial.py
cmsplugin_plaintext/migrations/0002_rename_plugin.py
cmsplugin_plaintext/migrations/__init__.py
cmsplugin_plaintext/templates/cmsplugin_plaintext/text.html
cmsplugin_plaintext_djangocms3.egg-info/PKG-INFO
cmsplugin_plaintext_djangocms3.egg-info/SOURCES.txt
cmsplugin_plaintext_djangocms3.egg-info/dependency_links.txt
cmsplugin_plaintext_djangocms3.egg-info/not-zip-safe
cmsplugin_plaintext_djangocms3.egg-info/top_level.txt