Metadata-Version: 1.0
Name: cmsplugin-plaintext-djangocms3
Version: 0.2.1
Summary: Adds a plaintext plugin for django-cms. Forked from https://bitbucket.org/xenofox/cmsplugin-plaintext to add django-cms3 support
Home-page: http://bitbucket.org/changer/cmsplugin-plaintext/
Author: Changer
Author-email: support@changer.nl
License: UNKNOWN
Platform: UNKNOWN
